LICENSE
README.md
setup.cfg
setup.py
pix/__init__.py
pix/api.py
pix/exc.py
pix/factory.py
pix/model.py
pix/utils.py
pix_api.egg-info/PKG-INFO
pix_api.egg-info/SOURCES.txt
pix_api.egg-info/dependency_links.txt
pix_api.egg-info/requires.txt
pix_api.egg-info/top_level.txt