Metadata-Version: 2.1
Name: pix-api
Version: 0.5.2
Summary: PIX Python API
Home-page: https://github.com/sambvfx/pix
Author: Sam Bourne
Author-email: sambvfx@gmail.com
License: UNKNOWN
Platform: UNKNOWN
Classifier: Development Status :: 4 - Beta
Classifier: Intended Audience :: Developers
Classifier: License :: OSI Approved :: MIT License
Classifier: Programming Language :: Python :: 2
Classifier: Programming Language :: Python :: 2.7
Classifier: Programming Language :: Python :: 3
Classifier: Programming Language :: Python :: 3.7
Provides-Extra: tests
